w2rpy_lite/__init__.py
w2rpy_lite/w2rpy_lite.py
w2rpy_lite-0.1.0.dist-info/METADATA
w2rpy_lite-0.1.0.dist-info/WHEEL
w2rpy_lite-0.1.0.dist-info/top_level.txt
w2rpy_lite-0.1.0.dist-info/RECORD
