Metadata-Version: 2.1
Name: w2rpy-lite
Version: 0.1.0
Requires-Python: <=3.11
Requires-Dist: pandas
Requires-Dist: numpy
Requires-Dist: shapely
Requires-Dist: geopandas
Requires-Dist: rasterio
Requires-Dist: pysheds
Requires-Dist: scipy
